{
    "rua": {
        "@_noNamespaceSchemaLocation": "file:/C:/Users/Cristiana%20Carvalho/Desktop/Publica%C3%A7%C3%A3o%20eletr%C3%B3nica/PROJETO%20FINAL/MRM-rua.xsd",
        "meta": {
            "número": "12",
            "nome": "Travessa Da Rua Do Forno Para A Do Poco"
        },
        "corpo": {
            "para": [
                {
                    "#text": "Mais um fragmento da grande, espinha dorsal doe que decalca uma.",
                    "lugar": [
                        "rua das Travessas",
                        "velho bairro medieval",
                        "velha rua romana"
                    ]
                },
                "Com construções de desigual desenho de fachada e características, esta é mais uma artéria que, lentamente, também foi perdendo a sua importância até aos finais do séc. XIX.",
                {
                    "#text": "Emfoi consideravelmente alargada, sendo destruídos todos os seus prédios, embora a linha de fachadas do lado Sul se tivesse mantido.",
                    "data": "1892"
                },
                {
                    "#text": "Hoje conservam-se apenas alguns pormenores da casa do prazo n.º 5, que era um belo edifício gótico e com pedra de armas: e onde, parece terem vivido familiares de, autor da «Geografia de Entre Douro e Minho».",
                    "entidade": {
                        "#text": "João de Barros",
                        "@_tipo": "pessoa"
                    }
                },
                "Extremamente curiosa é, também, a casa do prazo n.° 6. Com portão e janelas renascentistas, organiza-se em diferentes pisos, ligados por um muro oblíquo, descendo para o canto da rua. Sobre essa parte do edifício, tem um acréscimo, empoleirado, fazendo lembrar a arquitectura japonesa.",
                {
                    "#text": "Das 8 casas do lado Norte e 9 do lado Sul, são 4 e 6, respectivamente, prazos do.",
                    "entidade": {
                        "#text": "Cabido",
                        "@_tipo": "instituição"
                    }
                },
                {
                    "#text": "Hoje esta travessa é um troço nasituado entre ae a.",
                    "lugar": [
                        "rua D. Afonso Henriques",
                        "rua do Forno",
                        "rua D. Gonçalo Pereira"
                    ]
                }
            ],
            "figura": [
                {
                    "@_id": "MRB-12-norte",
                    "imagem": {
                        "@_path": "../imagem/MRB-12-TravessaDaRuaDoFornoParaADoPoco-Norte.jpg"
                    },
                    "legenda": "Travessa Da Rua Do Forno Para A Do Poço - vista norte."
                },
                {
                    "@_id": "MRB-12-sul",
                    "imagem": {
                        "@_path": "../imagem/MRB-12-TravessaDaRuaDoFornoParaADoPoco-Sul.jpg"
                    },
                    "legenda": "Travessa Da Rua Do Forno Para A Do Poço - vista sul."
                }
            ],
            "lista-casas": {
                "casa": [
                    {
                        "número": "1",
                        "enfiteuta": "Dr. Francisco Gomes do Couto",
                        "foro": "600 reis e 8 galinhas",
                        "desc": {
                            "para": {
                                "#text": "A casa n° 1 confronta, do nascente, com a. Fazem parte deste prazo os n° 15. 16, 17, 18 e 19, da. A casa n° 16 é foreira ao chantrado e paga de censo ao, ou seja. 54 reis.",
                                "lugar": [
                                    "Rua do Forno",
                                    "Rua do Forno ou dos Cegos"
                                ],
                                "entidade": {
                                    "#text": "cabido 2 maravedis",
                                    "@_tipo": "instituição"
                                }
                            }
                        }
                    },
                    {
                        "número": "2",
                        "foro": "108 reis (de censo)",
                        "desc": {
                            "para": {
                                "#text": "A casa n° 1 confronta, do nascente, com a. Fazem parte deste prazo os n° 15. 16, 17, 18 e 19, da. A casa n° 16 é foreira ao chantrado e paga de censo ao, ou seja. 54 reis.",
                                "lugar": [
                                    "Rua do Forno",
                                    "Rua do Forno ou dos Cegos"
                                ],
                                "entidade": {
                                    "#text": "cabido 2 maravedis",
                                    "@_tipo": "instituição"
                                }
                            }
                        }
                    },
                    {
                        "número": "3",
                        "enfiteuta": "Pedro da Cunha Sottomaior",
                        "foro": "1050 reis e 4 galinhas",
                        "desc": {
                            "para": {
                                "#text": "A casa n° 3 confronta, do sul, com ae,foi unida ao n° 4 em. A casa n.º 4 foi deixada ao., com encargo de um aniversário de três lições.",
                                "lugar": "Rua dos Palhais",
                                "data": "1622",
                                "entidade": [
                                    {
                                        "#text": "cabido pelo arcediago de Vermoim",
                                        "@_tipo": "instituição"
                                    },
                                    {
                                        "#text": "Francisco Fernandes",
                                        "@_tipo": "pessoa"
                                    }
                                ]
                            }
                        }
                    },
                    {
                        "número": "4",
                        "enfiteuta": "Pedro da Cunha Sottomaior",
                        "foro": "1050 reis e 4 galinhas",
                        "desc": {
                            "para": {
                                "#text": "A casa n° 3 confronta, do sul, com ae,foi unida ao n° 4 em. A casa n.º 4 foi deixada ao., com encargo de um aniversário de três lições.",
                                "lugar": "Rua dos Palhais",
                                "data": "1622",
                                "entidade": [
                                    {
                                        "#text": "cabido pelo arcediago de Vermoim",
                                        "@_tipo": "instituição"
                                    },
                                    {
                                        "#text": "Francisco Fernandes",
                                        "@_tipo": "pessoa"
                                    }
                                ]
                            }
                        }
                    },
                    {
                        "número": "5",
                        "foro": "54 reis (de censo)",
                        "desc": {
                            "para": {
                                "#text": "É foreira ao morgado de. O censo é pago por.",
                                "entidade": [
                                    {
                                        "#text": "Real",
                                        "@_tipo": "pessoa"
                                    },
                                    {
                                        "#text": "Lopo de Barros de Almeida",
                                        "@_tipo": "pessoa"
                                    }
                                ]
                            }
                        }
                    },
                    {
                        "número": "6",
                        "enfiteuta": "Padre António de Sousa e Alvim",
                        "foro": "400 reis e 1 galinha",
                        "desc": {
                            "para": {
                                "#text": "Situa-se na esquina dae\n                        confronta, do sul, com a casa n° 17 da dita rua. Pertence a este prazo o n.º 16, da.",
                                "lugar": [
                                    "Rua do Poço",
                                    "Rua de Santa Maria ou do Poço"
                                ]
                            }
                        }
                    },
                    {
                        "número": "7",
                        "enfiteuta": "Os herdeiros de João do Vale Campos",
                        "foro": "1200 reis e 8 galinhas",
                        "desc": {
                            "para": {
                                "#text": "Ao prazo n.º 7 foram unidos, em, dois ênxidos que se separaram dos n.º 13 e 14 dae, em. as casas dos referidos n.ºs.",
                                "data": [
                                    "1561",
                                    "1677"
                                ],
                                "lugar": "Rua do Poço"
                            }
                        }
                    },
                    {
                        "número": "8",
                        "desc": {
                            "para": {
                                "#text": "Corresponde ao n.° 2 da.",
                                "lugar": "Rua Pequena"
                            }
                        }
                    },
                    {
                        "número": "9",
                        "enfiteuta": "Os herdeiros de Henrique de Sousa e Alvim",
                        "foro": "330 reis e 2 galinhas",
                        "desc": {
                            "para": "Confronta, do nascente, com casa foreira à cororaria."
                        }
                    },
                    {
                        "número": "10",
                        "desc": {
                            "para": {
                                "#text": "Corresponde ao n.º 20 da, para onde tem a frontaria e serventia principais. Confronta, do poente, com casa foreira à cororaria.",
                                "lugar": "Rua do Forno"
                            }
                        }
                    }
                ]
            }
        }
    }
}